[{"id":"1","city":"Istanbul","country":" Turkey", "location":{"lon":"28.979530", "lat":"41.015137"}},
{"id":"2","city":"New York","country":" United State", "location":{"lon":"-73.935242", "lat":"40.730610"}},
{"id":"3","city":"London","country":" United Kingdom", "location":{"lon":"-0.118092", "lat":"51.509865"}},
{"id":"4","city":"Toronto","country":" Canada", "location":{"lon":"-79.347015", "lat":"43.651070"}},
{"id":"5","city":"Berlin","country":" Germany", "location":{"lon":"13.404954", "lat":"52.520008"}},
{"id":"6","city":"Madrid","country":" Spain", "location":{"lon":"-3.703790", "lat":"40.416775"}},
{"id":"7","city":"Kyiv","country":" Ukraine", "location":{"lon":"30.527561", "lat":"50.452194"}},
{"id":"8","city":"Rome","country":" Italy", "location":{"lon":"12.496366", "lat":"41.902782"}},
{"id":"9","city":"Paris","country":" France", "location":{"lon":"2.349014", "lat":"48.864716"}},
{"id":"10","city":"Bucharest","country":" Romania", "location":{"lon":"26.096306", "lat":"44.439663"}},
{"id":"11","city":"Miami","country":" United State", "location":{"lon":"-80.191788", "lat":"25.761681"}},
{"id":"12","city":"Vienna","country":" Austria", "location":{"lon":"16.363449", "lat":"48.210033"}},
{"id":"13","city":"Hamburg","country":" Germany", "location":{"lon":"9.993682", "lat":"53.551086"}},
{"id":"14","city":"Budapest","country":" Hungary", "location":{"lon":"19.040236", "lat":"47.497913"}},
{"id":"15","city":"Warsaw","country":" Poland", "location":{"lon":"21.017532", "lat":"52.237049"}},
{"id":"16","city":"Barcelona","country":" Spain", "location":{"lon":"2.154007", "lat":"41.390205"}},
{"id":"17","city":"Munich","country":" Germany", "location":{"lon":"11.576124", "lat":"48.137154"}},
{"id":"18","city":"Kharkiv","country":" Ukraine", "location":{"lon":"36.232845", "lat":"49.988358"}},
{"id":"19","city":"Milan","country":" Italy", "location":{"lon":"9.188540", "lat":"45.464664"}},
{"id":"20","city":"Prague","country":" Czech Republic", "location":{"lon":"14.418540", "lat":"50.073658"}},
{"id":"21","city":"Singapore","country":"Singapore", "location":{"lon":"103.851959", "lat":"1.290270"}},
{"id":"22","city":"Sofia","country":" Bulgaria", "location":{"lon":"23.319941", "lat":"42.698334"}},
{"id":"24","city":"Brussels","country":" Belgium", "location":{"lon":"4.3517103", "lat":"50.8503396"}},
{"id":"25","city":"Amsterdam","country":"Netherlands", "location":{"lon":"4.897070", "lat":"52.377956"}},
{"id":"26","city":"Belgrade","country":" Serbia", "location":{"lon":"20.457273", "lat":"44.787197"}},
{"id":"27","city":"Lisabon","country":" Portugal", "location":{"lon":"-9.142685", "lat":"38.736946"}},
{"id":"28","city":"Birmingham","country":" United Kingdom", "location":{"lon":"-1.898575", "lat":"52.489471"}},
{"id":"29","city":"Athens","country":" Greese", "location":{"lon":"23.727539", "lat":"37.983810"}},
{"id":"30","city":"Cologne","country":" Germany", "location":{"lon":"6.953101", "lat":"50.935173"}},
{"id":"31","city":"Oxford","country":" United Kingdom", "location":{"lon":"-1.257677", "lat":"51.752022"}},
{"id":"32","city":"Florence","country":" Italy", "location":{"lon":"11.255814", "lat":"43.769562"}},
{"id":"33","city":"Copenhagen","country":"Denmark", "location":{"lon":"12.568337", "lat":"55.676098"}},
{"id":"34","city":"Odesa","country":" Ukraine", "location":{"lon":"30.712481", "lat":"46.482952"}},
{"id":"35","city":"Naples","country":" Italy", "location":{"lon":"-81.806946", "lat":"26.177624"}},
{"id":"36","city":"Dnipro","country":" Ukraine", "location":{"lon":"34.983334", "lat":"48.450001"}},
{"id":"37","city":"Edinburgh","country":" Scotland", "location":{"lon":"-3.188267", "lat":"55.953251"}},
{"id":"38","city":"Dublin","country":" Ireland", "location":{"lon":"-6.266155", "lat":"53.350140"}},
{"id":"39","city":"Krakow","country":" Poland", "location":{"lon":"19.944544", "lat":"50.049683"}},
{"id":"40","city":"Los Angeles","country":" United State", "location":{"lon":"-118.243683", "lat":"34.052235"}},
{"id":"42","city":"Orlando","country":" United State", "location":{"lon":"-81.379234", "lat":"28.538336"}},
{"id":"43","city":"San Francisco","country":" United State", "location":{"lon":"-122.431297", "lat":"37.773972"}},
{"id":"44","city":"Las Vegas","country":" United State", "location":{"lon":"-115.176468", "lat":"36.188110"}},
{"id":"45","city":"Honolulu","country":" United State", "location":{"lon":"-157.858093", "lat":"21.315603"}},
{"id":"46","city":"Washington","country":" United State", "location":{"lon":"-120.740135", "lat":"47.751076"}},
{"id":"47","city":"Boston","country":" United State", "location":{"lon":"-71.057083", "lat":"42.361145"}},
{"id":"48","city":"Chicago","country":" United State", "location":{"lon":"-87.623177", "lat":"41.881832"}},
{"id":"49","city":"Edmonton","country":" Canada", "location":{"lon":"-113.323975", "lat":"53.631611"}},
{"id":"50","city":"Ottawa","country":" Canada", "location":{"lon":"-75.695000", "lat":"45.424721"}},
{"id":"51","city":"Quebec City","country":" Canada", "location":{"lon":"-71.254028", "lat":"46.829853"}},
{"id":"52","city":"Vancouver","country":" Canada", "location":{"lon":"-123.116226", "lat":"49.246292"}},
{"id":"53","city":"Calgary","country":" Canada", "location":{"lon":"-114.066666", "lat":"51.049999"}},
{"id":"54","city":"Winnipeg","country":" Canada", "location":{"lon":"-97.138451", "lat":"49.895077"}}
]